repose/__init__.py
repose/api.py
repose/apibackend.py
repose/decoders.py
repose/encoders.py
repose/exceptions.py
repose/fields.py
repose/helpers.py
repose/managers.py
repose/resources.py
repose/utilities.py
repose/validators.py
repose/tests/__init__.py
repose/tests/test_fields.py
repose/tests/test_managers.py
repose/tests/test_resource.py
repose/tests/test_utilities.py
repose/tests/test_validators.py
repose-0.1.1.dist-info/DESCRIPTION.rst
repose-0.1.1.dist-info/METADATA
repose-0.1.1.dist-info/metadata.json
repose-0.1.1.dist-info/RECORD
repose-0.1.1.dist-info/top_level.txt
repose-0.1.1.dist-info/WHEEL
