Metadata-Version: 2.0
Name: repose
Version: 0.1.1
Summary: Quickly create restful API clients in Python
Home-page: http://github.com/adamcharnock/repose
Author: Adam Charnock
Author-email: adam@adamcharnock.com
License: UNKNOWN
Platform: UNKNOWN
Requires-Dist: booby (==0.7.0)
Requires-Dist: requests (==2.7.0)
Requires-Dist: six
